{
 "id": "8212",
 "name": "may-the-odds-be-ever-in-your-favor-cmapocalypse-bingo-2012",
 "title": "May The Odds Be Ever In Your Favor: CMApocalypse Bingo 2012",
 "author": "Morgan Levy",
 "date": "2012-06-06T00:45:00-05:00",
 "tags": [
  "cma music fetsival",
  "cmapocalypse",
  "cmapocalypse 2012",
  "cmapocalypse bingo"
 ],
 "categories": [],
 "contentEncoded": "<p><a href=\"http://i46.tinypic.com/25hn282.jpg\" target=\"_blank\"><img class=\"alignnone size-full wp-image-8214\" title=\"cmapocalypsebingo12_web\" src=\"http://nashvillest.com/wp-content/uploads/2012/06/cmapocalypsebingo12_web.jpg\" alt=\"\" width=\"475\" height=\"615\"></a></p>\n<p>Running a little late this year due to an unfortunate hard drive crash at Nashvillest HQ, but we&#x2019;re back up and running and have your 2012 CMApocalypse Bingo board, just in time for the kickoff parade festivities! <em>A big thanks to our&#xA0;Twitter (and real life) friends @<a href=\"http://twitter.com/txmere\" target=\"_blank\">txmere</a>, @<a href=\"http://twitter.com/freakyweasel\" target=\"_blank\">freakyweasel</a>, @<a href=\"http://twitter.com/thesarcastro\" target=\"_blank\">thesarcastro</a>, @<a href=\"http://twitter.com/loveandnachos\" target=\"_blank\">loveandnachos</a>, @<a href=\"http://twitter.com/blakeboldt\" target=\"_blank\">blakeboldt</a>, @<a href=\"http://twitter.com/tabbulous\" target=\"_blank\">tabbulous</a>, @<a href=\"http://twitter.com/lesleyest\" target=\"_blank\">lesleyest</a>, @<a href=\"http://twitter.com/iamaledelgado\" target=\"_blank\">iamaledelgado</a>, @<a href=\"http://twitter.com/aduthie\" target=\"_blank\">aduthie</a>, @<a href=\"http://twitter.com/missbethd\" target=\"_blank\">missbethd</a>, @<a href=\"http://twitter.com/ceeelcee\" target=\"_blank\">ceeelcee</a>, @<a href=\"http://twitter.com/lesleyrebecca\" target=\"_blank\">lesleyrebecca</a>, @<a href=\"http://twitter.com/megmo\" target=\"_blank\">megmo</a>, @<a href=\"http://twitter.com/lucastypes\" target=\"_blank\">lucastypes</a>, @<a href=\"http://twitter.com/dannylondon\" target=\"_blank\">dannylondon</a> and @<a href=\"http://twitter.com/alisongroves\" target=\"_blank\">alisongroves</a> for help with this year&#x2019;s bingo board. We couldn&#x2019;t do it without you!</em></p>\n<p>(This year&#x2019;s bingo too easy? Let&#x2019;s see you take on past year&#x2019;s boards: <a href=\"http://nashvillest.com/2011/06/06/let-the-games-begin-cmapocalypse-bingo-2011/\" target=\"_blank\">2011</a>, <a href=\"http://nashvillest.com/2010/06/08/let-the-games-begin-cmapocalypse-bingo-2010/\" target=\"_blank\">2010</a>, <a href=\"http://nashvillest.com/2009/06/11/the-official-nashvillest-2009-cmapocalypse-bingo-card/\" target=\"_blank\">2009</a>, <a href=\"http://nashvillest.com/2008/06/04/fan-fair-bingo-when-youre-done-counting-tube-tops-cmapocalypse-2008/\" target=\"_blank\">2008</a>)</p>\n<p><a href=\"http://i46.tinypic.com/25hn282.jpg\" target=\"_blank\">Giant sized CMApocalypse Bingo 2012 board</a><br>\n<a href=\"http://nashvillest.com/wp-content/uploads/2012/06/cmapocalypsebingo12_sm.jpg\" target=\"_blank\">Pocket sized CMApocalypse Bingo 2012 board<br>\n</a><a href=\"http://cmabingo.thomasruns.com/login_main.php\" target=\"_blank\">Mobile CMApocalypse Bingo 2012 board</a> <em>(thanks, <a href=\"http://thomasruns.com/\" target=\"_blank\">Thomas</a>!)</em></p>"
}